[
    {
        "_id": "61b215ad293def0a3c69c8ee",
        "name": "Chú già nuôi mèo ú",
        "slugName": "chu-gia-nuoi-meo-u"
    },
    {
        "_id": "61b215fccdb551739da359cf",
        "name": "Bên dưới cây cầu Arakawa",
        "slugName": "ben-duoi-cay-cau-arakawa"
    },
    {
        "_id": "61b21622af11e59e50088c63",
        "name": "Naruto",
        "slugName": "naruto"
    },
    {
        "_id": "61b21641af11e59e50088c65",
        "name": "Black Clover",
        "slugName": "black-clover"
    },
    {
        "_id": "61b21673af11e59e50088c67",
        "name": "'Cậu' ma nhà xí Hanako",
        "slugName": "cau-ma-nha-xi-hanako"
    },
    {
        "_id": "61b2168baf11e59e50088c69",
        "name": "One Piece",
        "slugName": "one-piece"
    },
    {
        "_id": "61b216ccaf11e59e50088c6b",
        "name": "Dr.Stone",
        "slugName": "dr-stone"
    },
    {
        "_id": "61b216e4af11e59e50088c6d",
        "name": "Yêu thương cho con",
        "slugName": "yeu-thuong-cho-con"
    },
    {
        "_id": "61b216faaf11e59e50088c6f",
        "name": "Đội quân nhí nhố",
        "slugName": "doi-quan-nhi-nho"
    },
    {
        "_id": "61b21716af11e59e50088c71",
        "name": "Say cool to English",
        "slugName": "say-cool-to-english"
    },
    {
        "_id": "61b2174baf11e59e50088c73",
        "name": "Kiến thức lịch sử",
        "slugName": "kien-thuc-lich-su"
    },
    {
        "_id": "61b21766af11e59e50088c75",
        "name": "Disney - Tạp chí thế giới ô tô",
        "slugName": "disney-tap-chi-the-gioi-o-to"
    },
    {
        "_id": "61b2177eaf11e59e50088c77",
        "name": "Hướng nghiệp 4.0",
        "slugName": "huong-nghiep-4-0"
    },
    {
        "_id": "61b217a5af11e59e50088c79",
        "name": "Hồi kí Vanitas",
        "slugName": "hoi-ki-vanitas"
    },
    {
        "_id": "61b217bdaf11e59e50088c7b",
        "name": "Hiểu về tài chính, vững bước tương lai",
        "slugName": "hieu-ve-tai-chinh-vung-buoc-tuong-lai"
    },
    {
        "_id": "61b217d5af11e59e50088c7d",
        "name": "Từ những hạt mầm",
        "slugName": "tu-nhung-hat-mam"
    },
    {
        "_id": "61b217efaf11e59e50088c7f",
        "name": "Dế mèn phiêu lưu ký",
        "slugName": "de-men-phieu-luu-ky"
    },
    {
        "_id": "61b21806af11e59e50088c81",
        "name": "Tủ sách vàng",
        "slugName": "tu-sach-vang"
    }
]